rtl/von_neumann.v
`timescale 1ns / 1ps
module von_neumann (
    input  wire clk,
    input  wire rst,
    input  wire enable,
    input  wire bit_in,
    output reg  bit_out,
    output reg  valid
);
    reg state;
    reg buffer;

    always @(posedge clk) begin
        if (rst) begin
            bit_out <= 1'b0;
            valid   <= 1'b0;
            state   <= 1'b0;
            buffer  <= 1'b0;
        end else if (enable) begin
            if (state == 0) begin
                buffer <= bit_in;
                state  <= 1'b1;
                valid  <= 1'b0;
            end else begin
                state <= 1'b0;
                if (buffer != bit_in) begin
                    bit_out <= buffer;
                    valid   <= 1'b1;
                end else begin
                    valid   <= 1'b0;
                end
            end
        end
    end
endmodule

rtl/entropy_sampler.v
`timescale 1ns / 1ps
module entropy_sampler (
    input  wire clk,
    input  wire rst,
    input  wire enable,
    input  wire entropy_in,
    output reg  sampled_bit
);
    always @(posedge clk) begin
        if (rst) sampled_bit <= 1'b0;
        else if (enable) sampled_bit <= entropy_in;
    end
endmodule

rtl/ring_oscillator.v
`timescale 1ns / 1ps
module ring_oscillator #(
    parameter DELAY = 1  // Valoare implicită
)(
    input  wire enable,
    output wire ro_out
);
    wire n1, n2, n3;

    // Folosim parametrul DELAY pentru a varia viteza
    assign #DELAY n1 = ~(n3 & enable); 
    assign #(DELAY) n2 = ~n1;
    assign #(DELAY) n3 = ~n2;

    assign ro_out = n3;
endmodule

rtl/trng_top.v
`timescale 1ns / 1ps
module trng_top (
    input  wire clk,
    input  wire rst,
    input  wire enable,
    output wire random_bit,
    output wire random_valid
);
    wire [7:0] ro_bits;
    wire combined_entropy;
    wire sampled_entropy;

    genvar i;
    generate
        for (i = 0; i < 8; i = i + 1) begin : ro_gen
            // Pasăm un DELAY diferit pentru fiecare instanță (i+1)
            ring_oscillator #(.DELAY(i + 1)) ro_inst (
                .enable(enable),
                .ro_out(ro_bits[i])
            );
        end
    endgenerate

    // XOR Combiner - acum va funcționa pentru că RO-urile au viteze diferite!
    assign combined_entropy = ^ro_bits;

    entropy_sampler sampler (
        .clk(clk),
        .rst(rst),
        .enable(enable),
        .entropy_in(combined_entropy),
        .sampled_bit(sampled_entropy)
    );

    von_neumann vn (
        .clk(clk),
        .rst(rst),
        .enable(enable),
        .bit_in(sampled_entropy),
        .bit_out(random_bit),
        .valid(random_valid)
    );
endmodule

tb/trng_top_tb.v
`timescale 1ns / 1ps
module trng_top_tb;
    reg clk, rst, enable;
    wire random_bit, random_valid;

    trng_top dut (.clk(clk), .rst(rst), .enable(enable), .random_bit(random_bit), .random_valid(random_valid));

    always #5 clk = ~clk;

    initial begin
        clk = 0; enable = 0; rst = 1;
        #50 rst = 0;
        #20 enable = 1;
        #100000; 
        $finish;
    end

    initial begin
        $dumpfile("trng_wave.vcd");
        $dumpvars(0, trng_top_tb);
    end
endmodule

trng_wave.vcd
$date
	Fri Jan  9 14:02:42 2026
$end
$version
	Icarus Verilog
$end
$timescale
	1ps
$end
$scope module trng_top_tb $end
$var wire 1 ! random_valid $end
$var wire 1 " random_bit $end
$var reg 1 # clk $end
$var reg 1 $ enable $end
$var reg 1 % rst $end
$scope module dut $end
$var wire 1 # clk $end
$var wire 1 $ enable $end
$var wire 1 % rst $end
$var wire 1 & sampled_entropy $end
$var wire 8 ' ro_bits [7:0] $end
$var wire 1 ! random_valid $end
$var wire 1 " random_bit $end
$var wire 1 ( combined_entropy $end
$scope begin ro_gen[0] $end
$var parameter 2 ) i $end
$scope module ro_inst $end
$var wire 1 $ enable $end
$var wire 1 * n1 $end
$var wire 1 + n2 $end
$var wire 1 , n3 $end
$var wire 1 - ro_out $end
$var parameter 32 . DELAY $end
$upscope $end
$upscope $end
$scope begin ro_gen[1] $end
$var parameter 2 / i $end
$scope module ro_inst $end
$var wire 1 $ enable $end
$var wire 1 0 n1 $end
$var wire 1 1 n2 $end
$var wire 1 2 n3 $end
$var wire 1 3 ro_out $end
$var parameter 32 4 DELAY $end
$upscope $end
$upscope $end
$scope begin ro_gen[2] $end
$var parameter 3 5 i $end
$scope module ro_inst $end
$var wire 1 $ enable $end
$var wire 1 6 n1 $end
$var wire 1 7 n2 $end
$var wire 1 8 n3 $end
$var wire 1 9 ro_out $end
$var parameter 32 : DELAY $end
$upscope $end
$upscope $end
$scope begin ro_gen[3] $end
$var parameter 3 ; i $end
$scope module ro_inst $end
$var wire 1 $ enable $end
$var wire 1 < n1 $end
$var wire 1 = n2 $end
$var wire 1 > n3 $end
$var wire 1 ? ro_out $end
$var parameter 32 @ DELAY $end
$upscope $end
$upscope $end
$scope begin ro_gen[4] $end
$var parameter 4 A i $end
$scope module ro_inst $end
$var wire 1 $ enable $end
$var wire 1 B n1 $end
$var wire 1 C n2 $end
$var wire 1 D n3 $end
$var wire 1 E ro_out $end
$var parameter 32 F DELAY $end
$upscope $end
$upscope $end
$scope begin ro_gen[5] $end
$var parameter 4 G i $end
$scope module ro_inst $end
$var wire 1 $ enable $end
$var wire 1 H n1 $end
$var wire 1 I n2 $end
$var wire 1 J n3 $end
$var wire 1 K ro_out $end
$var parameter 32 L DELAY $end
$upscope $end
$upscope $end
$scope begin ro_gen[6] $end
$var parameter 4 M i $end
$scope module ro_inst $end
$var wire 1 $ enable $end
$var wire 1 N n1 $end
$var wire 1 O n2 $end
$var wire 1 P n3 $end
$var wire 1 Q ro_out $end
$var parameter 32 R DELAY $end
$upscope $end
$upscope $end
$scope begin ro_gen[7] $end
$var parameter 4 S i $end
$scope module ro_inst $end
$var wire 1 $ enable $end
$var wire 1 T n1 $end
$var wire 1 U n2 $end
$var wire 1 V n3 $end
$var wire 1 W ro_out $end
$var parameter 32 X DELAY $end
$upscope $end
$upscope $end
$scope module sampler $end
$var wire 1 # clk $end
$var wire 1 $ enable $end
$var wire 1 ( entropy_in $end
$var wire 1 % rst $end
$var reg 1 & sampled_bit $end
$upscope $end
$scope module vn $end
$var wire 1 & bit_in $end
$var wire 1 # clk $end
$var wire 1 $ enable $end
$var wire 1 % rst $end
$var reg 1 " bit_out $end
$var reg 1 Y buffer $end
$var reg 1 Z state $end
$var reg 1 ! valid $end
$upscope $end
$upscope $end
$upscope $end
$enddefinitions $end
$comment Show the parameter values. $end
$dumpall
b1000 X
b111 S
b111 R
b110 M
b110 L
b101 G
b101 F
b100 A
b100 @
b11 ;
b11 :
b10 5
b10 4
b1 /
b1 .
b0 )
$end
#0
$dumpvars
xZ
xY
xW
xV
xU
xT
xQ
xP
xO
xN
xK
xJ
xI
xH
xE
xD
xC
xB
x?
x>
x=
x<
x9
x8
x7
x6
x3
x2
x1
x0
x-
x,
x+
x*
x(
bx '
x&
1%
0$
0#
x"
x!
$end
#1000
1*
#2000
0+
10
#3000
bx1 '
1-
1,
16
#4000
01
1<
#5000
0&
0Y
0Z
0!
0"
1B
1#
#6000
bx11 '
13
12
07
1H
#7000
1N
#8000
0=
1T
#9000
bx111 '
19
18
#10000
0C
0#
#12000
bx1111 '
1?
1>
0I
#14000
0O
#15000
bx11111 '
1E
1D
1#
#16000
0U
#18000
bx111111 '
1K
1J
#20000
0#
#21000
bx1111111 '
1Q
1P
#24000
0(
b11111111 '
1W
1V
#25000
1#
#30000
0#
#35000
1#
#40000
0#
#45000
1#
#50000
0#
0%
#55000
1#
#60000
0#
#65000
1#
#70000
0#
1$
#71000
0*
#72000
1+
00
#73000
1(
b11111110 '
0-
0,
06
#74000
1*
11
0<
#75000
1Z
1&
0+
0B
1#
#76000
1-
1,
1(
b11111101 '
03
02
17
0H
#77000
0*
0N
#78000
1+
10
1=
0T
#79000
0-
0,
1(
b11111000 '
09
08
#80000
1*
01
1C
0#
#81000
0+
#82000
1-
1,
13
12
16
0(
b11110011 '
0?
0>
1I
#83000
0*
#84000
1+
00
1O
#85000
0&
1!
0Z
0-
0,
07
0(
b11100010 '
0E
0D
1#
#86000
1*
11
1<
1U
#87000
0+
#88000
1-
1,
03
02
19
18
0(
b11000101 '
0K
0J
#89000
0*
#90000
1+
10
0=
1B
0#
#91000
0-
0,
06
0(
b10000100 '
0Q
0P
#92000
1*
01
#93000
0+
#94000
1-
1,
13
12
17
1?
1>
1H
0(
b1111 '
0W
0V
#95000
0!
1Z
0*
0C
1#
#96000
1+
00
#97000
0-
0,
0(
b1010 '
09
08
#98000
1*
11
0<
1N
#99000
0+
#100000
1-
1,
03
02
16
1(
b11001 '
1E
1D
0#
0I
#101000
0*
#102000
1+
10
1=
1T
#103000
0(
b11000 '
0-
0,
07
#104000
1*
01
#105000
0Z
0+
0B
1#
0O
#106000
1-
1,
13
12
19
18
0?
0>
1(
b110111 '
1K
1J
#107000
0*
#108000
1+
00
#109000
0(
b110110 '
0-
0,
06
#110000
1*
11
1<
1C
0#
0U
#111000
0+
#112000
1-
1,
03
02
17
0H
1(
b1110101 '
1Q
1P
#113000
0*
#114000
1+
10
0=
#115000
1Z
0-
0,
09
08
0(
b1100000 '
0E
0D
1#
#116000
1*
01
#117000
0+
#118000
1-
1,
13
12
16
1?
1>
1I
0(
b11101011 '
1W
1V
#119000
0*
0N
#120000
1+
00
1B
0#
#121000
1(
b11101010 '
0-
0,
07
#122000
1*
11
0<
#123000
0+
#124000
1-
1,
03
02
19
18
1(
b11001101 '
0K
0J
#125000
1&
0Z
0*
0C
1#
#126000
1+
10
1=
1O
0T
#127000
0(
b11001100 '
0-
0,
06
#128000
1*
01
#129000
0+
#130000
1-
1,
13
12
17
0?
0>
0(
b11010111 '
1E
1D
0#
1H
#131000
0*
#132000
1+
00
#133000
0-
0,
09
08
1(
b10010010 '
0Q
0P
#134000
1*
11
1<
1U
#135000
1Z
1Y
0+
0B
1#
#136000
1-
1,
1(
b10010001 '
03
02
16
0I
#137000
0*
#138000
1+
10
0=
#139000
0(
b10010000 '
0-
0,
07
#140000
1*
01
1C
0#
1N
#141000
0+
#142000
1-
1,
13
12
19
18
1?
1>
1K
1J
0(
b111111 '
0W
0V
#143000
0*
#144000
1+
00
#145000
0&
0Z
0-
0,
06
0(
b101110 '
0E
0D
1#
#146000
1*
11
0<
#147000
0+
0O
#148000
1-
1,
0(
b101101 '
03
02
17
0H
#149000
0*
#150000
1+
10
1=
1B
0#
1T
#151000
0-
0,
0(
b101000 '
09
08
#152000
1*
01
#153000
0+
#154000
1-
1,
13
12
16
0?
0>
1I
0(
b1100011 '
1Q
1P
#155000
1Z
0Y
0*
0C
1#
#156000
1+
00
#157000
1(
b1100010 '
0-
0,
07
#158000
1*
11
1<
0U
#159000
0+
#160000
1-
1,
03
02
19
18
1E
1D
0#
0(
b1010101 '
0K
0J
#161000
0*
0N
#162000
1+
10
0=
#163000
1(
b1010100 '
0-
0,
06
#164000
1*
01
#165000
1&
0Z
0+
0B
1#
#166000
1-
1,
13
12
17
1?
1>
1H
1(
b11011111 '
1W
1V
#167000
0*
#168000
1+
00
1O
#169000
0-
0,
1(
b11011010 '
09
08
#170000
1*
11
0<
1C
0#
#171000
0+
#172000
1-
1,
1(
b11011001 '
03
02
16
0I
#173000
0*
#174000
1+
10
1=
0T
#175000
1Z
1Y
0&
0-
0,
07
0E
0D
1#
0(
b10001000 '
0Q
0P
#176000
1*
01
#177000
0+
#178000
1-
1,
13
12
19
18
0?
0>
1(
b10100111 '
1K
1J
#179000
0*
#180000
1+
00
1B
0#
#181000
0(
b10100110 '
0-
0,
06
#182000
1*
11
1<
1N
1U
#183000
0+
#184000
1-
1,
0(
b10100101 '
03
02
17
0H
#185000
1!
1"
0Z
0*
0C
1#
#186000
1+
10
0=
#187000
0-
0,
0(
b10100000 '
09
08
#188000
1*
01
#189000
0+
0O
#190000
1-
1,
13
12
16
1?
1>
1E
1D
0#
1I
1(
b111011 '
0W
0V
#191000
0*
#192000
1+
00
#193000
0(
b111010 '
0-
0,
07
#194000
1*
11
0<
#195000
0!
1Z
0Y
0+
0B
1#
#196000
1-
1,
03
02
19
18
0K
0J
1(
b1011101 '
1Q
1P
#197000
0*
#198000
1+
10
1=
1T
#199000
0(
b1011100 '
0-
0,
06
#200000
1*
01
1C
0#
#201000
0+
#202000
1-
1,
13
12
17
1(
b1010111 '
0?
0>
1H
#203000
0*
0N
#204000
1+
00
#205000
0Z
0-
0,
09
08
0(
b1000010 '
0E
0D
1#
#206000
1*
11
1<
0U
#207000
0+
#208000
1-
1,
0(
b1000001 '
03
02
16
0I
#209000
0*
#210000
1+
10
0=
1B
0#
1O
#211000
1(
b1000000 '
0-
0,
07
#212000
1*
01
#213000
0+
#214000
1-
1,
13
12
19
18
1?
1>
1K
1J
1(
b11101111 '
1W
1V
#215000
1Z
1&
0*
0C
1#
#216000
1+
00
#217000
0-
0,
06
1(
b10101110 '
0Q
0P
#218000
1*
11
0<
#219000
0+
#220000
1-
1,
03
02
17
0(
b10111101 '
1E
1D
0#
0H
#221000
0*
#222000
1+
10
1=
0T
#223000
0-
0,
0(
b10111000 '
09
08
#224000
1*
01
1N
#225000
0&
1!
0"
0Z
0+
0B
1#
#226000
1-
1,
13
12
16
1(
b10110011 '
0?
0>
1I
#227000
0*
#228000
1+
00
#229000
0(
b10110010 '
0-
0,
07
#230000
1*
11
1<
1C
0#
1U
#231000
0+
0O
#232000
1-
1,
03
02
19
18
0(
b10010101 '
0K
0J
#233000
0*
#234000
1+
10
0=
#235000
0!
1Z
0-
0,
06
0(
b10000100 '
0E
0D
1#
#236000
1*
01
#237000
0+
#238000
1-
1,
13
12
17
1?
1>
1H
1Q
1P
1(
b1001111 '
0W
0V
#239000
0*
#240000
1+
00
1B
0#
#241000
0-
0,
1(
b1001010 '
09
08
#242000
1*
11
0<
#243000
0+
#244000
1-
1,
1(
b1001001 '
03
02
16
0I
#245000
1&
0Z
0*
0C
1#
0N
#246000
1+
10
1=
1T
#247000
0(
b1001000 '
0-
0,
07
#248000
1*
01
#249000
0+
#250000
1-
1,
13
12
19
18
0?
0>
1E
1D
0#
0(
b1110111 '
1K
1J
#251000
0*
#252000
1+
00
1O
#253000
1(
b1110110 '
0-
0,
06
#254000
1*
11
1<
0U
#255000
1Z
1Y
0+
0B
1#
#256000
1-
1,
1(
b1110101 '
03
02
17
0H
#257000
0*
#258000
1+
10
0=
#259000
0-
0,
09
08
0(
b110000 '
0Q
0P
#260000
1*
01
1C
0#
#261000
0+
#262000
1-
1,
13
12
16
1?
1>
1I
0(
b10111011 '
1W
1V
#263000
0*
#264000
1+
00
#265000
0&
0Z
0-
0,
07
0(
b10101010 '
0E
0D
1#
#266000
1*
11
0<
1N
#267000
0+
#268000
1-
1,
03
02
19
18
0(
b10001101 '
0K
0J
#269000
0*
#270000
1+
10
1=
1B
0#
0T
#271000
1(
b10001100 '
0-
0,
06
#272000
1*
01
#273000
0+
0O
#274000
1-
1,
13
12
17
0(
b10000111 '
0?
0>
1H
#275000
1Z
0Y
0*
0C
1#
#276000
1+
00
#277000
0-
0,
0(
b10000010 '
09
08
#278000
1*
11
1<
1U
#279000
0+
#280000
1-
1,
03
02
16
1E
1D
0#
0I
0(
b11010001 '
1Q
1P
#281000
0*
#282000
1+
10
0=
#283000
1(
b11010000 '
0-
0,
07
#284000
1*
01
#285000
1&
0Z
0+
0B
1#
#286000
1-
1,
13
12
19
18
1?
1>
1K
1J
1(
b1111111 '
0W
0V
#287000
0*
0N
#288000
1+
00
#289000
0(
b1111110 '
0-
0,
06
#290000
1*
11
0<
1C
0#
#291000
0+
#292000
1-
1,
0(
b1111101 '
03
02
17
0H
#293000
0*
#294000
1+
10
1=
1O
1T
#295000
1Z
1Y
0-
0,
09
08
1(
b1101000 '
0E
0D
1#
#296000
1*
01
#297000
0+
#298000
1-
1,
13
12
16
0(
b1100011 '
0?
0>
1I
#299000
0*
#300000
1+
00
1B
0#
#301000
0-
0,
07
0(
b100010 '
0Q
0P
#302000
1*
11
1<
0U
#303000
0+
#304000
1-
1,
03
02
19
18
0(
b101 '
0K
0J
#305000
0&
0Z
0*
0C
1#
#306000
1+
10
0=
#307000
1(
b100 '
0-
0,
06
#308000
1*
01
1N
#309000
0+
#310000
1-
1,
13
12
17
1?
1>
1E
1D
0#
1H
0(
b10011111 '
1W
1V
#311000
0*
#312000
1+
00
#313000
0-
0,
0(
b10011010 '
09
08
#314000
1*
11
0<
#315000
1Z
0Y
0+
0B
1#
0O
#316000
1-
1,
0(
b10011001 '
03
02
16
0I
#317000
0*
#318000
1+
10
1=
0T
#319000
1(
b10011000 '
0-
0,
07
#320000
1*
01
1C
0#
#321000
0+
#322000
1-
1,
13
12
19
18
0?
0>
1K
1J
1(
b11110111 '
1Q
1P
#323000
0*
#324000
1+
00
#325000
1&
0Z
0-
0,
06
1(
b11100110 '
0E
0D
1#
#326000
1*
11
1<
1U
#327000
0+
#328000
1-
1,
1(
b11100101 '
03
02
17
0H
#329000
0*
0N
#330000
1+
10
0=
1B
0#
#331000
0-
0,
1(
b11100000 '
09
08
#332000
1*
01
#333000
0+
#334000
1-
1,
13
12
16
1?
1>
1I
1(
b1101011 '
0W
0V
#335000
1Z
1Y
0*
0C
1#
#336000
1+
00
1O
#337000
0(
b1101010 '
0-
0,
07
#338000
1*
11
0<
#339000
0+
#340000
1-
1,
03
02
19
18
1E
1D
0#
1(
b1011101 '
0K
0J
#341000
0*
#342000
1+
10
1=
1T
#343000
0-
0,
06
1(
b11100 '
0Q
0P
#344000
1*
01
#345000
0Z
0+
0B
1#
#346000
1-
1,
13
12
17
0(
b10111 '
0?
0>
1H
#347000
0*
#348000
1+
00
#349000
0-
0,
0(
b10010 '
09
08
#350000
1*
11
1<
1C
0#
1N
0U
#351000
0+
#352000
1-
1,
0(
b10001 '
03
02
16
0I
#353000
0*
#354000
1+
10
0=
#355000
1Z
0&
0-
0,
07
0(
b0 '
0E
0D
1#
#356000
1*
01
#357000
0+
0O
#358000
1-
1,
13
12
19
18
1?
1>
1K
1J
0(
b10101111 '
1W
1V
#359000
0*
#360000
1+
00
1B
0#
#361000
1(
b10101110 '
0-
0,
06
#362000
1*
11
0<
#363000
0+
#364000
1-
1,
03
02
17
0H
0(
b11101101 '
1Q
1P
#365000
1!
1"
0Z
0*
0C
1#
#366000
1+
10
1=
0T
#367000
0-
0,
0(
b11101000 '
09
08
#368000
1*
01
#369000
0+
#370000
1-
1,
13
12
16
0?
0>
0(
b11110011 '
1E
1D
0#
1I
#371000
0*
0N
#372000
1+
00
#373000
1(
b11110010 '
0-
0,
07
#374000
1*
11
1<
1U
#375000
0!
1Z
0Y
1&
0+
0B
1#
#376000
1-
1,
03
02
19
18
1(
b11010101 '
0K
0J
#377000
0*
#378000
1+
10
0=
1O
#379000
0(
b11010100 '
0-
0,
06
#380000
1*
01
1C
0#
#381000
0+
#382000
1-
1,
13
12
17
1?
1>
1H
0(
b1011111 '
0W
0V
#383000
0*
#384000
1+
00
#385000
0&
1!
0"
0Z
0-
0,
09
08
0E
0D
1#
0(
b1010 '
0Q
0P
#386000
1*
11
0<
#387000
0+
#388000
1-
1,
0(
b1001 '
03
02
16
0I
#389000
0*
#390000
1+
10
1=
1B
0#
1T
#391000
1(
b1000 '
0-
0,
07
#392000
1*
01
1N
#393000
0+
#394000
1-
1,
13
12
19
18
0?
0>
0(
b100111 '
1K
1J
#395000
0!
1Z
0*
0C
1#
#396000
1+
00
#397000
1(
b100110 '
0-
0,
06
#398000
1*
11
1<
0U
#399000
0+
0O
#400000
1-
1,
03
02
17
0(
b110101 '
1E
1D
0#
0H
#401000
0*
#402000
1+
10
0=
#403000
0-
0,
0(
b110000 '
09
08
#404000
1*
01
#405000
0Z
0+
0B
1#
#406000
1-
1,
13
12
16
1?
1>
1I
1Q
1P
1(
b11111011 '
1W
1V
#407000
0*
#408000
1+
00
#409000
0(
b11111010 '
0-
0,
07
#410000
1*
11
0<
1C
0#
#411000
0+
#412000
1-
1,
03
02
19
18
0(
b11011101 '
0K
0J
#413000
0*
0N
#414000
1+
10
1=
0T
#415000
1Z
0-
0,
06
0(
b11001100 '
0E
0D
1#
#416000
1*
01
#417000
0+
#418000
1-
1,
13
12
17
1(
b11000111 '
0?
0>
1H
#419000
0*
#420000
1+
00
1B
0#
1O
#421000
0-
0,
1(
b11000010 '
09
08
#422000
1*
11
1<
1U
#423000
0+
#424000
1-
1,
1(
b11000001 '
03
02
16
0I
#425000
1&
0Z
0*
0C
1#
#426000
1+
10
0=
#427000
0-
0,
07
1(
b10000000 '
0Q
0P
#428000
1*
01
#429000
0+
#430000
1-
1,
13
12
19
18
1?
1>
1E
1D
0#
1K
1J
0(
b111111 '
0W
0V
#431000
0*
#432000
1+
00
#433000
1(
b111110 '
0-
0,
06
#434000
1*
11
0<
1N
#435000
1Z
1Y
0+
0B
1#
#436000
1-
1,
1(
b111101 '
03
02
17
0H
#437000
0*
#438000
1+
10
1=
1T
#439000
0-
0,
1(
b111000 '
09
08
#440000
1*
01
1C
0#
#441000
0+
0O
#442000
1-
1,
13
12
16
0(
b110011 '
0?
0>
1I
#443000
0*
#444000
1+
00
#445000
0&
0Z
0-
0,
07
0(
b100010 '
0E
0D
1#
#446000
1*
11
1<
0U
#447000
0+
#448000
1-
1,
03
02
19
18
0K
0J
1(
b1000101 '
1Q
1P
#449000
0*
#450000
1+
10
0=
1B
0#
#451000
0(
b1000100 '
0-
0,
06
#452000
1*
01
#453000
0+
#454000
1-
1,
13
12
17
1?
1>
1H
0(
b11001111 '
1W
1V
#455000
1Z
0Y
0*
0C
1#
0N
#456000
1+
00
#457000
0-
0,
0(
b11001010 '
09
08
#458000
1*
11
0<
#459000
0+
#460000
1-
1,
03
02
16
1(
b11011001 '
1E
1D
0#
0I
#461000
0*
#462000
1+
10
1=
1O
0T
#463000
0(
b11011000 '
0-
0,
07
#464000
1*
01
#465000
0Z
0+
0B
1#
#466000
1-
1,
13
12
19
18
0?
0>
1(
b11110111 '
1K
1J
#467000
0*
#468000
1+
00
#469000
0-
0,
06
1(
b10110110 '
0Q
0P
#470000
1*
11
1<
1C
0#
1U
#471000
0+
#472000
1-
1,
1(
b10110101 '
03
02
17
0H
#473000
0*
#474000
1+
10
0=
#475000
1Z
0-
0,
09
08
0(
b10100000 '
0E
0D
1#
#476000
1*
01
1N
#477000
0+
#478000
1-
1,
13
12
16
1?
1>
1I
0(
b101011 '
0W
0V
#479000
0*
#480000
1+
00
1B
0#
#481000
1(
b101010 '
0-
0,
07
#482000
1*
11
0<
#483000
0+
0O
#484000
1-
1,
03
02
19
18
1(
b1101 '
0K
0J
#485000
1&
0Z
0*
0C
1#
#486000
1+
10
1=
1T
#487000
0(
b1100 '
0-
0,
06
#488000
1*
01
#489000
0+
#490000
1-
1,
13
12
17
0?
0>
1E
1D
0#
1H
1(
b1010111 '
1Q
1P
#491000
0*
#492000
1+
00
#493000
0-
0,
1(
b1010010 '
09
08
#494000
1*
11
1<
0U
#495000
1Z
1Y
0+
0B
1#
#496000
1-
1,
1(
b1010001 '
03
02
16
0I
#497000
0*
0N
#498000
1+
10
0=
#499000
0(
b1010000 '
0-
0,
07
#500000
1*
01
1C
0#
#501000
0+
#502000
1-
1,
13
12
19
18
1?
1>
1K
1J
0(
b11111111 '
1W
1V
#503000
0*
#504000
1+
00
1O
#505000
0&
0Z
0-
0,
06
0(
b11101110 '
0E
0D
1#
#506000
1*
11
0<
#507000
0+
#508000
1-
1,
0(
b11101101 '
03
02
17
0H
#509000
0*
#510000
1+
10
1=
1B
0#
0T
#511000
0-
0,
09
08
1(
b10101000 '
0Q
0P
#512000
1*
01
#513000
0+
#514000
1-
1,
13
12
16
0(
b10100011 '
0?
0>
1I
#515000
1Z
0Y
0*
0C
1#
#516000
1+
00
#517000
1(
b10100010 '
0-
0,
07
#518000
1*
11
1<
1N
1U
#519000
0+
#520000
1-
1,
03
02
19
18
1E
1D
0#
0(
b10010101 '
0K
0J
#521000
0*
#522000
1+
10
0=
#523000
1(
b10010100 '
0-
0,
06
#524000
1*
01
#525000
1&
0Z
0+
0B
1#
0O
#526000
1-
1,
13
12
17
1?
1>
1H
1(
b11111 '
0W
0V
#527000
0*
#528000
1+
00
#529000
0-
0,
1(
b11010 '
09
08
#530000
1*
11
0<
1C
0#
#531000
0+
#532000
1-
1,
03
02
16
0I
0(
b1011001 '
1Q
1P
#533000
0*
#534000
1+
10
1=
1T
#535000
1Z
1Y
0&
0-
0,
07
0(
b1001000 '
0E
0D
1#
#536000
1*
01
#537000
0+
#538000
1-
1,
13
12
19
18
0?
0>
1(
b1100111 '
1K
1J
#539000
0*
0N
#540000
1+
00
1B
0#
#541000
0(
b1100110 '
0-
0,
06
#542000
1*
11
1<
0U
#543000
0+
#544000
1-
1,
0(
b1100101 '
03
02
17
0H
#545000
1!
1"
0Z
0*
0C
1#
#546000
1+
10
0=
1O
#547000
0-
0,
0(
b1100000 '
09
08
#548000
1*
01
#549000
0+
#550000
1-
1,
13
12
16
1?
1>
1E
1D
0#
1I
1(
b11111011 '
1W
1V
#551000
0*
#552000
1+
00
#553000
0-
0,
07
1(
b10111010 '
0Q
0P
#554000
1*
11
0<
#555000
0!
1Z
0Y
1&
0+
0B
1#
#556000
1-
1,
03
02
19
18
1(
b10011101 '
0K
0J
#557000
0*
#558000
1+
10
1=
0T
#559000
0(
b10011100 '
0-
0,
06
#560000
1*
01
1C
0#
1N
#561000
0+
#562000
1-
1,
13
12
17
1(
b10010111 '
0?
0>
1H
#563000
0*
#564000
1+
00
#565000
0&
1!
0"
0Z
0-
0,
09
08
0(
b10000010 '
0E
0D
1#
#566000
1*
11
1<
1U
#567000
0+
0O
#568000
1-
1,
0(
b10000001 '
03
02
16
0I
#569000
0*
#570000
1+
10
0=
1B
0#
#571000
1(
b10000000 '
0-
0,
07
#572000
1*
01
#573000
0+
#574000
1-
1,
13
12
19
18
1?
1>
1K
1J
1Q
1P
0(
b1101111 '
0W
0V
#575000
0!
1Z
0*
0C
1#
#576000
1+
00
#577000
1(
b1101110 '
0-
0,
06
#578000
1*
11
0<
#579000
0+
#580000
1-
1,
03
02
17
0(
b1111101 '
1E
1D
0#
0H
#581000
0*
0N
#582000
1+
10
1=
1T
#583000
0-
0,
0(
b1111000 '
09
08
#584000
1*
01
#585000
0Z
0+
0B
1#
#586000
1-
1,
13
12
16
1(
b1110011 '
0?
0>
1I
#587000
0*
#588000
1+
00
1O
#589000
0(
b1110010 '
0-
0,
07
#590000
1*
11
1<
1C
0#
0U
#591000
0+
#592000
1-
1,
03
02
19
18
0(
b1010101 '
0K
0J
#593000
0*
#594000
1+
10
0=
#595000
1Z
1&
0-
0,
06
0E
0D
1#
1(
b100 '
0Q
0P
#596000
1*
01
#597000
0+
#598000
1-
1,
13
12
17
1?
1>
1H
1(
b10001111 '
1W
1V
#599000
0*
#600000
1+
00
1B
0#
#601000
0-
0,
1(
b10001010 '
09
08
#602000
1*
11
0<
1N
#603000
0+
#604000
1-
1,
1(
b10001001 '
03
02
16
0I
#605000
1!
0Z
0*
0C
1#
#606000
1+
10
1=
0T
#607000
0(
b10001000 '
0-
0,
07
#608000
1*
01
#609000
0+
0O
#610000
1-
1,
13
12
19
18
0?
0>
1E
1D
0#
0(
b10110111 '
1K
1J
#611000
0*
#612000
1+
00
#613000
1(
b10110110 '
0-
0,
06
#614000
1*
11
1<
1U
#615000
0!
1Z
1Y
0+
0B
1#
#616000
1-
1,
03
02
17
0H
0(
b11110101 '
1Q
1P
#617000
0*
#618000
1+
10
0=
#619000
0-
0,
0(
b11110000 '
09
08
#620000
1*
01
1C
0#
#621000
0+
#622000
1-
1,
13
12
16
1?
1>
1I
0(
b1111011 '
0W
0V
#623000
0*
0N
#624000
1+
00
#625000
0&
0Z
0-
0,
07
0(
b1101010 '
0E
0D
1#
#626000
1*
11
0<
#627000
0+
#628000
1-
1,
03
02
19
18
0(
b1001101 '
0K
0J
#629000
0*
#630000
1+
10
1=
1B
0#
1O
1T
#631000
1(
b1001100 '
0-
0,
06
#632000
1*
01
#633000
0+
#634000
1-
1,
13
12
17
0(
b1000111 '
0?
0>
1H
#635000
1Z
0Y
0*
0C
1#
#636000
1+
00
#637000
0-
0,
09
08
1(
b10 '
0Q
0P
#638000
1*
11
1<
0U
#639000
0+
#640000
1-
1,
03
02
16
0(
b10001 '
1E
1D
0#
0I
#641000
0*
#642000
1+
10
0=
#643000
1(
b10000 '
0-
0,
07
#644000
1*
01
1N
#645000
1&
0Z
0+
0B
1#
#646000
1-
1,
13
12
19
18
1?
1>
1K
1J
1(
b10111111 '
1W
1V
#647000
0*
#648000
1+
00
#649000
0(
b10111110 '
0-
0,
06
#650000
1*
11
0<
1C
0#
#651000
0+
0O
#652000
1-
1,
0(
b10111101 '
03
02
17
0H
#653000
0*
#654000
1+
10
1=
0T
#655000
1Z
1Y
0-
0,
09
08
1(
b10101000 '
0E
0D
1#
#656000
1*
01
#657000
0+
#658000
1-
1,
13
12
16
0?
0>
1I
1(
b11100011 '
1Q
1P
#659000
0*
#660000
1+
00
1B
0#
#661000
0(
b11100010 '
0-
0,
07
#662000
1*
11
1<
1U
#663000
0+
#664000
1-
1,
03
02
19
18
0(
b11000101 '
0K
0J
#665000
0&
0Z
0*
0C
1#
0N
#666000
1+
10
0=
#667000
1(
b11000100 '
0-
0,
06
#668000
1*
01
#669000
0+
#670000
1-
1,
13
12
17
1?
1>
1E
1D
0#
1H
0(
b1011111 '
0W
0V
#671000
0*
#672000
1+
00
1O
#673000
0-
0,
0(
b1011010 '
09
08
#674000
1*
11
0<
#675000
1Z
0Y
0+
0B
1#
#676000
1-
1,
0(
b1011001 '
03
02
16
0I
#677000
0*
#678000
1+
10
1=
1T
#679000
0-
0,
07
0(
b11000 '
0Q
0P
#680000
1*
01
1C
0#
#681000
0+
#682000
1-
1,
13
12
19
18
0?
0>
1(
b110111 '
1K
1J
#683000
0*
#684000
1+
00
#685000
1&
0Z
0-
0,
06
1(
b100110 '
0E
0D
1#
